pyzxz/__init__.py
pyzxz/pyzxz.py
pyzxz-0.1.0.dist-info/licenses/LICENSE
pyzxz-0.1.0.dist-info/METADATA
pyzxz-0.1.0.dist-info/WHEEL
pyzxz-0.1.0.dist-info/top_level.txt
pyzxz-0.1.0.dist-info/RECORD
