Metadata-Version: 2.4
Name: pyzxz
Version: 0.1.0
Summary: A Python client for 0x0.st file hosting service.
Author-email: cvcvka5 <cvcvka5@gmail.com>
License: MIT License
Classifier: Programming Language :: Python :: 3
Classifier: License :: OSI Approved :: MIT License
Classifier: Operating System :: OS Independent
Requires-Python: >=3.7
License-File: LICENSE
Requires-Dist: requests
Dynamic: license-file
